XMLWirelessWindows/__init__.py
XMLWirelessWindows/algorithms.py
XMLWirelessWindows/createXMLfile.py
XMLWirelessWindows-0.1.3.4.dist-info/LICENSE
XMLWirelessWindows-0.1.3.4.dist-info/METADATA
XMLWirelessWindows-0.1.3.4.dist-info/WHEEL
XMLWirelessWindows-0.1.3.4.dist-info/top_level.txt
XMLWirelessWindows-0.1.3.4.dist-info/RECORD
