Metadata-Version: 2.1
Name: XMLWirelessWindows
Version: 0.1.3.4
Summary: Create, Edit and Change Infomation of XML File
Home-page: https://github.com/nguyentranphucbao/XMLWirelessWindows
Author: @KudoKuro
Author-email: nguyentranphucbao@gmail.com
License: UNKNOWN
Platform: UNKNOWN
Classifier: Programming Language :: Python :: 3
Classifier: License :: OSI Approved :: MIT License
Classifier: Operating System :: OS Independent
Requires-Python: >=3.5
